{
  "book_id": "系统之美：决策者的系统思考 = Thinking in Systems a Primer ([美] 唐內拉‧梅多斯 (D",
  "book_title": "系统之美：决策者的系统思考",
  "concepts": [
    {
      "name": "系统",
      "description": "在书中的含义：系统不是一堆事物的集合，而是由要素、相互连接关系与共同目标构成的整体。梅多斯强调，系统之所以呈现某种行为，不是因为部件本身，而是因为部件如何连接、朝什么目标运转。 作者为何强调：因为多数人看问题停留在“零件视角”，以为增加资源、替换负责人、修改某个环节就够了，却忽略整体行为来自结构。",
      "importance": "high"
    },
    {
      "name": "库存与流量",
      "description": "在书中的含义：库存是某一时刻积累起来的状态量，流量是改变库存的进入与流出。库存让系统具有记忆，流量决定库存如何变化。 作者为何强调：因为人们容易只对“流量事件”有感知，比如订单、收入、流入人口、污染排放，却忽略真正决定后果的是积累状态，比如负债、声誉、人口结构、碳浓度、信任储备。",
      "importance": "high"
    },
    {
      "name": "反馈回路",
      "description": "在书中的含义：反馈回路是系统行为得以自我生成、自我纠偏或自我放大的机制。主要分为强化回路与调节回路。强化回路让变化越来越快，调节回路让系统维持在某种范围。 作者为何强调：因为线性思维只看到单向作用，而反馈思维看到“结果会反过来成为原因”。这使我们能理解增长、崩溃、稳定、振荡等行为模式。",
      "importance": "high"
    },
    {
      "name": "时间延迟",
      "description": "在书中的含义：延迟是行动与结果之间的时间间隔。系统中的许多失误并非出于错误目标，而是因为决策者对延迟缺乏耐心或理解，过早加码、反复修正，最终诱发振荡和失稳。 作者为何强调：因为延迟会让人误判因果。我们经常在效果尚未显现时就以为原方案无效，或者在坏后果尚未出现时误以为当前做法成功。",
      "importance": "high"
    },
    {
      "name": "杠杆点",
      "description": "在书中的含义：杠杆点是系统中一个小改变能够引发大变化的位置。梅多斯后半部分最著名的贡献之一，就是提出不同层级杠杆点的高低之分：参数较浅，信息流、规则、目标、范式较深。 作者为何强调：因为决策者很容易把力气花在最显眼、最易操作但最不根本的地方，比如调数字、增预算、换口号，而忽略真正有穿透力的结构位置。",
      "importance": "high"
    },
    {
      "name": "韧性与自组织",
      "description": "在书中的含义：系统不仅会运行，还会适应、恢复、重组。韧性是系统承受冲击后维持核心功能的能力，自组织是系统在内部生成新结构、新模式的能力。 作者为何强调：因为很多管理者只追求效率与控制，却忽略真正可持续的系统必须保留冗余、多样性、缓冲空间和学习能力。",
      "importance": "high"
    },
    {
      "name": "心智模型 / 范式",
      "description": "在书中的含义：系统之下还有更深层的东西，即决策者用来理解世界的假设、价值观和默认因果图。梅多斯把范式视为最高阶杠杆点之一，因为它决定我们看见什么、忽略什么、如何定义“成功”。 作者为何强调：因为许多失败不是技术问题，而是理解框架错了。若仍把经济理解为无限增长机器，就很难真正重视生态边界；若仍把组织理解为服从机器，就难建立学习型协作。",
      "importance": "high"
    }
  ],
  "themes": [],
  "viewpoints": [
    {
      "title": "模块一：系统基础——从“看见部件”到“看见关系”",
      "points": [
        "表面在讲什么：介绍系统、要素、连接、目标、库存与流量的基础定义。",
        "在全书中的功能：建立读者的基本观察语言，让后续关于反馈、行为模式与杠杆点的讨论有共同坐标。",
        "与前后内容衔接：这是入口部分；如果没有这一层，读者很容易把后面所有内容误解成抽象隐喻。"
      ]
    },
    {
      "title": "模块二：动态行为——反馈、延迟与非线性如何塑造现实",
      "points": [
        "表面在讲什么：系统为何会增长、振荡、失稳、崩溃，反馈回路和时间延迟在其中起什么作用。",
        "在全书中的功能：把“系统存在”推进到“系统如何行动”，让结构与行为建立可理解的桥梁。",
        "与前后内容衔接：承接基础概念，并为后文识别系统陷阱和寻找杠杆点提供动态机制解释。"
      ]
    },
    {
      "title": "模块三：系统陷阱——为什么好意经常制造坏结果",
      "points": [
        "表面在讲什么：公地悲剧、目标侵蚀、转嫁负担、恶性竞争、成功者更成功等常见系统原型。",
        "在全书中的功能：把抽象机制转成现实可识别的“失败模式”，帮助读者在工作和社会中迅速识别结构性困境。",
        "与前后内容衔接：从机制走向诊断，说明前文不是理论游戏，而是现实问题识别工具。"
      ]
    },
    {
      "title": "模块四：杠杆点——怎样改变系统，而不只是干预表象",
      "points": [
        "表面在讲什么：系统中不同层级的干预位置，从参数到范式，影响力与难度如何排序。",
        "在全书中的功能：这是从“理解系统”走向“改变系统”的关键转折，也是决策者最想知道、也最容易误用的一部分。",
        "与前后内容衔接：前文解释了系统为何这样运作，这部分回答“那我们到底该从哪里下手”。"
      ]
    },
    {
      "title": "模块五：与系统共舞——系统思考的伦理与实践姿态",
      "points": [
        "表面在讲什么：面对复杂系统，应该怎样观察、试错、保持谦逊、与不确定性合作。",
        "在全书中的功能：防止读者把系统思考再一次误用成新的控制术。",
        "与前后内容衔接：在识别杠杆点之后，作者提醒改变系统并非操控系统，而是更成熟地参与系统。"
      ]
    },
    {
      "title": "观点1：系统结构比个体意图更能解释长期结果",
      "points": [
        "表面在说什么：很多结果不是谁故意造成的，而是结构持续诱发的。",
        "更深层在回应什么：它回应的是“为什么好人会做出坏结果，为什么聪明组织仍会集体失灵”。",
        "作者为何强调：因为道德归因太容易，结构分析太困难；人们本能想找责任人，而不是看激励与反馈如何塑形。"
      ]
    },
    {
      "title": "观点2：反馈与延迟让复杂系统天然违背直觉",
      "points": [
        "表面在说什么：系统中的因果关系常有循环与滞后，因此直觉式干预容易失手。",
        "更深层在回应什么：它回应的是“为什么经验丰富的管理者，也会在复杂问题上反复判断失真”。",
        "作者为何强调：因为人类在进化上更适应短链因果，不擅长感知慢变量和远后果。"
      ]
    },
    {
      "title": "观点3：高杠杆点通常不在参数，而在规则、目标与范式",
      "points": [
        "表面在说什么：最有效的改变，往往不是多加一点资源，而是改信息流、改规则、改目标。",
        "更深层在回应什么：它回应的是“为什么我们做了很多正确动作，却仍然收效有限”。",
        "作者为何强调：因为现实决策最容易选择浅层可控项，却回避深层高冲突项。"
      ]
    },
    {
      "title": "观点4：追求效率而牺牲韧性，会让系统在冲击中崩得更快",
      "points": [
        "表面在说什么：冗余、多样性、缓冲看似低效，却是长期存活的必要条件。",
        "更深层在回应什么：它回应的是现代管理中“把一切闲置都当浪费”的单一效率逻辑。",
        "作者为何强调：因为很多系统在平时表现优秀，恰恰掩盖了其对异常事件的脆弱。"
      ]
    },
    {
      "title": "观点5：真正成熟的系统思考，不是更强控制，而是学会与系统共舞",
      "points": [
        "表面在说什么：面对复杂系统，最好的姿态是观察、试探、反馈、修正，而非一把抓全局。",
        "更深层在回应什么：它回应的是现代人对确定性和可控性的执念。",
        "作者为何强调：因为一旦把系统思考变成控制术，它就背离了自己对复杂性的尊重。"
      ]
    }
  ],
  "quotes": [
    {
      "text": "一个系统不仅仅是许多事物的集合。",
      "source": "— 对应命题：系统由要素、连接与目标构成；重要性在于纠正“堆零件=系统”的误解。"
    },
    {
      "text": "系统的行为来自其结构。",
      "source": "— 对应命题：结构决定行为；这是全书最核心判断之一。"
    },
    {
      "text": "反馈回路是系统行为的秘密所在。",
      "source": "— 对应命题：理解反馈，才能理解增长、稳定与崩溃。"
    },
    {
      "text": "库存是变化的记忆，流量是变化的方式。",
      "source": "— 对应命题：库存—流量帮助我们看到慢变量与累积后果。"
    },
    {
      "text": "系统往往让我们最后才看到真正重要的东西。",
      "source": "— 对应命题：延迟与累积使人类对关键状态变化感知迟钝。"
    },
    {
      "text": "原因和结果在复杂系统中并不总是紧邻出现。",
      "source": "— 对应命题：批判线性、近距因果直觉。"
    },
    {
      "text": "今天的问题，常常来自昨天的解决方案。",
      "source": "— 对应命题：系统陷阱与政策反噬；点出短期解法的长期代价。"
    },
    {
      "text": "越是显眼的地方，往往越不是高杠杆点。",
      "source": "— 对应命题：提醒不要只盯参数与表层动作。"
    },
    {
      "text": "改变数字很容易，改变目标很难，改变范式更难。",
      "source": "— 对应命题：杠杆点分层；深层改变更有力量也更困难。"
    },
    {
      "text": "系统的真实目标，是它持续表现出来的行为。",
      "source": "— 对应命题：不要只听口号，要看长期输出。"
    }
  ],
  "keywords": [
    "反馈回路",
    "系统",
    "杠杆点",
    "心智模型 / 范式",
    "库存与流量",
    "韧性与自组织",
    "时间延迟"
  ]
}